{"appleSKU":"","appleTeamID":"","enableCodelessAutoInitialization":true,"enableUnityGamingServicesAutoInitialization":false,"products":[{"id":"com.carrotstore.pomodoroclock.removeads","type":1,"storeIDs":[],"defaultDescription":{"googleLocale":4,"title":"Remove Ads","description":"Not show ads in app"},"screenshotPath":"","applePriceTier":0,"googlePrice":{"data":[32,0,0,0],"num":32.0},"pricingTemplateID":"","descriptions":[],"udpPrice":{"data":[0,0,0,0],"num":0.0},"payouts":[]},{"id":"com.carrotstore.pomodoroclock.bk","type":0,"storeIDs":[],"defaultDescription":{"googleLocale":4,"title":"Background Music","description":"Buy a background music"},"screenshotPath":"","applePriceTier":0,"googlePrice":{"data":[11,0,0,0],"num":11.0},"pricingTemplateID":"","descriptions":[],"udpPrice":{"data":[0,0,0,0],"num":0.0},"payouts":[]}]}